pyearth/__init__.py
pyearth/gis/__init__.py
pyearth/gis/envi/__init__.py
pyearth/gis/envi/envi_write_header.py
pyearth/gis/gdal/__init__.py
pyearth/gis/gdal/gdal_check_file_type.py
pyearth/gis/gdal/gdal_check_raster_valid.py
pyearth/gis/gdal/gdal_raster_format_support.py
pyearth/gis/gdal/gdal_to_numpy_datatype.py
pyearth/gis/gdal/gdal_validate_polygon_file.py
pyearth/gis/gdal/gdal_vector_format_support.py
pyearth/gis/gdal/read/__init__.py
pyearth/gis/gdal/read/raster/__init__.py
pyearth/gis/gdal/read/raster/gdal_get_raster_extent.py
pyearth/gis/gdal/read/raster/gdal_get_raster_spatial_reference.py
pyearth/gis/gdal/read/raster/gdal_read_ascii_file.py
pyearth/gis/gdal/read/raster/gdal_read_envi_file.py
pyearth/gis/gdal/read/raster/gdal_read_geotiff_file.py
pyearth/gis/gdal/read/vector/__init__.py
pyearth/gis/gdal/read/vector/gdal_get_vector_boundary.py
pyearth/gis/gdal/read/vector/gdal_get_vector_extent.py
pyearth/gis/gdal/read/vector/gdal_get_vector_spatial_reference.py
pyearth/gis/gdal/read/vector/gdal_read_vector_file.py
pyearth/gis/gdal/write/__init__.py
pyearth/gis/gdal/write/raster/__init__.py
pyearth/gis/gdal/write/raster/gdal_write_envi_file.py
pyearth/gis/gdal/write/raster/gdal_write_geotiff_file.py
pyearth/gis/gdal/write/vector/__init__.py
pyearth/gis/gdal/write/vector/gdal_export_vertex_to_vector_file.py
pyearth/gis/gdal/write/vector/gdal_write_wkt_to_vector_file.py
pyearth/gis/geometry/__init__.py
pyearth/gis/geometry/calculate_angle_between_vectors_degrees.py
pyearth/gis/geometry/calculate_angle_between_vertex.py
pyearth/gis/geometry/calculate_angle_between_vertex_normal.py
pyearth/gis/geometry/calculate_distance_based_on_longitude_latitude.py
pyearth/gis/geometry/calculate_distance_to_line.py
pyearth/gis/geometry/calculate_distance_to_plane.py
pyearth/gis/geometry/calculate_intersect_on_great_circle.py
pyearth/gis/geometry/calculate_polygon_area.py
pyearth/gis/geometry/calculate_spherical_triangle_area.py
pyearth/gis/geometry/clean_geometry.py
pyearth-0.1.28.dist-info/licenses/LICENSE.md
pyearth-0.1.28.dist-info/METADATA
pyearth-0.1.28.dist-info/WHEEL
pyearth-0.1.28.dist-info/top_level.txt
pyearth-0.1.28.dist-info/RECORD
