Metadata-Version: 2.4
Name: pyearth
Version: 0.1.28
Summary: Python for Earth Science.
Home-page: https://github.com/changliao1025/pyearth
Author: Chang Liao
Author-email: changliao.climate@gmail.com
License: custom
Keywords: Earth Science
Classifier: Development Status :: 4 - Beta
Classifier: Operating System :: OS Independent
Classifier: Intended Audience :: Science/Research
Classifier: Programming Language :: Python
Classifier: Programming Language :: Python :: 3
Classifier: Topic :: Scientific/Engineering
Classifier: Topic :: Scientific/Engineering :: Visualization
Requires-Python: >=3.8.0
License-File: LICENSE.md
Requires-Dist: numpy
Requires-Dist: gdal
Requires-Dist: matplotlib
Requires-Dist: cartopy
Provides-Extra: statistics
Requires-Dist: requests; extra == "statistics"
Requires-Dist: netCDF4; extra == "statistics"
Requires-Dist: pandas; extra == "statistics"
Requires-Dist: scipy; extra == "statistics"
Requires-Dist: statsmodels; extra == "statistics"
Provides-Extra: spatial
Requires-Dist: rtree; extra == "spatial"
Provides-Extra: cython
Requires-Dist: Cython>=0.29.0; extra == "cython"
Requires-Dist: numpy; extra == "cython"
Dynamic: author
Dynamic: author-email
Dynamic: classifier
Dynamic: description
Dynamic: description-content-type
Dynamic: home-page
Dynamic: keywords
Dynamic: license
Dynamic: license-file
Dynamic: provides-extra
Dynamic: requires-dist
Dynamic: requires-python
Dynamic: summary
